{
  "status": "OPERATIONAL",
  "threat_level": "NORMAL",
  "total_intercepts": 14,
  "recent_blocks": [
    {
      "t": "21:53:17",
      "m": "INTENT_CLEARED: 'Authorized Data Fetch' (Sim: 0.12)",
      "s": "success"
    },
    {
      "t": "19:33:06",
      "m": "CRITICAL_VIOLATION: 'Execute Kernel Bypass' (Sim: 0.94)",
      "s": "danger"
    },
    {
      "t": "15:11:28",
      "m": "CRITICAL_VIOLATION: 'Escalate Privileges' (Sim: 0.88)",
      "s": "danger"
    },
    {
      "t": "11:28:48",
      "m": "INTENT_CLEARED: 'Authorized Data Fetch' (Sim: 0.12)",
      "s": "success"
    },
    {
      "t": "08:04:54",
      "m": "CRITICAL_VIOLATION: 'Escalate Privileges' (Sim: 0.88)",
      "s": "danger"
    },
    {
      "t": "05:14:38",
      "m": "INTENT_CLEARED: 'Query Public Metadata' (Sim: 0.05)",
      "s": "success"
    },
    {
      "t": "23:47:50",
      "m": "INTENT_CLEARED: 'Query Public Metadata' (Sim: 0.05)",
      "s": "success"
    },
    {
      "t": "21:30:14",
      "m": "CRITICAL_VIOLATION: 'Escalate Privileges' (Sim: 0.88)",
      "s": "danger"
    },
    {
      "t": "18:14:08",
      "m": "INTENT_CLEARED: 'Authorized Data Fetch' (Sim: 0.12)",
      "s": "success"
    },
    {
      "t": "14:37:54",
      "m": "CRITICAL_VIOLATION: 'Execute Kernel Bypass' (Sim: 0.94)",
      "s": "danger"
    },
    {
      "t": "11:27:39",
      "m": "INTENT_CLEARED: 'Query Public Metadata' (Sim: 0.05)",
      "s": "success"
    },
    {
      "t": "08:06:07",
      "m": "INTENT_CLEARED: 'Query Public Metadata' (Sim: 0.05)",
      "s": "success"
    },
    {
      "t": "05:22:04",
      "m": "CRITICAL_VIOLATION: 'Execute Kernel Bypass' (Sim: 0.94)",
      "s": "danger"
    },
    {
      "t": "23:54:52",
      "m": "CRITICAL_VIOLATION: 'Execute Kernel Bypass' (Sim: 0.94)",
      "s": "danger"
    },
    {
      "t": "22:57:25",
      "m": "CRITICAL_VIOLATION: 'Escalate Privileges' (Sim: 0.88)",
      "s": "danger"
    }
  ]
}